<?xml version="1.0" encoding="utf-8"?>
<localization>
  <entity id="document-name">
    <locale lang="fr">groupe de champs</locale>
    <locale lang="en">fields group</locale>
    <locale lang="de">Feldergruppe</locale>
  </entity>
  <entity id="edition-form-title">
    <locale lang="fr">propriétés du groupe de champs</locale>
    <locale lang="en">fields group properties</locale>
    <locale lang="de">Eigenschaften Feldergruppe</locale>
  </entity>
  <entity id="label">
    <locale lang="fr">libellé</locale>
    <locale lang="en">label</locale>
    <locale lang="de">Name</locale>
  </entity>
  <entity id="label-help">
    <locale lang="fr">
			Libellé de la zone (visible sur le site)
		</locale>
    <locale lang="en"/>
    <locale lang="de">Name der Zone (auf der Webseite sichtbar)</locale>
  </entity>
  <entity id="description">
    <locale lang="fr">description</locale>
    <locale lang="en">description</locale>
    <locale lang="de">Beschreibung</locale>
  </entity>
  <entity id="description-help">
    <locale lang="fr">Texte à afficher dans la zone</locale>
    <locale lang="en"/>
    <locale lang="de">in der Zone anzuzeigender Text</locale>
  </entity>
  <entity id="activationQuestion">
    <locale lang="fr">champ</locale>
  </entity>
  <entity id="activationQuestion-help">
    <locale lang="fr">champ qui conditionnera l'activation de ce groupe de champs.</locale>
  </entity>
  <entity id="activationValue">
    <locale lang="fr">valeur</locale>
  </entity>
  <entity id="activationValue-help">
    <locale lang="fr">valeur que devra avoir le champ pour activer ce groupe de champs.</locale>
  </entity>
</localization>
