<?xml version="1.0" encoding="utf-8"?>
<localization>
  <entity id="document-name">
    <locale lang="fr">champ caché</locale>
    <locale lang="en">hidden field</locale>
    <locale lang="de">verstecktes Feld</locale>
  </entity>
  <entity id="edition-form-title">
    <locale lang="fr">propriétés du champ caché</locale>
    <locale lang="en">hidden field's properties</locale>
    <locale lang="de">Eigenschaften verstecktes Feld</locale>
  </entity>
  <entity id="label">
    <locale lang="fr">libellé</locale>
    <locale lang="en">label</locale>
    <locale lang="de">Name</locale>
  </entity>
  <entity id="label-help">
    <locale lang="fr">
			libellé du champ caché (ne sera pas affiché sur le site)
		</locale>
    <locale lang="en">hidden field's label</locale>
    <locale lang="de">Name verstecktes Feld (wird nicht auf der Webseite angezeigt)</locale>
  </entity>
  <entity id="fieldName">
    <locale lang="fr">nom du champ</locale>
    <locale lang="en">field name</locale>
    <locale lang="de">Feldname</locale>
  </entity>
  <entity id="fieldName-help">
    <locale lang="fr">
			Le nom du champ doit être composé de lettres et de chiffres
			uniquement et doit commencer par une lettre.
		</locale>
    <locale lang="en">
			The field name must be composed of letters and digits and
			must begin with a letter.
		</locale>
    <locale lang="de">Der Feldname muss ausschliesslich aus Buchstaben und Ziffern bestehen und muss mit einem Buchstaben beginnen</locale>
  </entity>
  <entity id="validators">
    <locale lang="fr">validateurs</locale>
    <locale lang="en">validators</locale>
    <locale lang="de">Bestätiger</locale>
  </entity>
  <entity id="validators-help">
    <locale lang="fr">
			Liste des validateurs du champ, séparés par des
			points-virgules.
		</locale>
    <locale lang="en">
			validators list for the field, separated by semicolons.
		</locale>
    <locale lang="de">Bestätigerliste des Feldes, durch Punkt-Kommata getrennt.</locale>
  </entity>
  <entity id="required">
    <locale lang="fr">champ obligatoire</locale>
    <locale lang="en">required field</locale>
    <locale lang="de">obligatorisches Feld</locale>
  </entity>
  <entity id="required-help">
    <locale lang="fr">champ obligatoire</locale>
    <locale lang="en">required field</locale>
    <locale lang="de">obligatorisches Feld</locale>
  </entity>
  <entity id="isReceiver">
    <locale lang="fr">champ destinataire du mail</locale>
    <locale lang="en">field of mail receiver</locale>
    <locale lang="de">Feld Empfänger der E-mail</locale>
  </entity>
  <entity id="isReceiver-help">
    <locale lang="fr">
			Détermine si ce champ caché devra comprendre le contact
			destinataire de l'email
		</locale>
    <locale lang="en">
			Define if this hidden field must contain receiver contact of
			email
		</locale>
    <locale lang="de">Bestimmt ob dieses versteckte Feld den Empfängerkontakt beinhalten muss</locale>
  </entity>
  <entity id="isRecommand">
    <locale lang="fr">champ recommander à un ami</locale>
    <locale lang="de">Feld einem Freund empfehlen</locale>
  </entity>
  <entity id="isRecommand-help">
    <locale lang="fr">
			Champ utilisé pour la fonction recommander à un ami
		</locale>
    <locale lang="de">Feld für die Funktion einem Freund empfehlen</locale>
  </entity>
</localization>
